{
	"$schema": "./list.schema.json",
	"content": [
		{
			"Name": "AliYun",
			"Description": "AliYun (Alibaba Cloud)",
			"Postpone": 0,
			"APT": [ ],
			"Chocolatey": [ ],
			"Homebrew": [
				"aliyun-cli"
			],
			"NPM": [ ],
			"Pipx": [ ],
			"Env": [ ],
			"PathLinux": [
				"/usr/local/bin/aliyun"
			],
			"PathMacOS": [ ],
			"PathWindows": [
				"C:\\aliyun-cli"
			]
		},
		{
			"Name": "AndroidNDK",
			"Description": "Android NDK",
			"Postpone": 0,
			"APT": [ ],
			"Chocolatey": [ ],
			"Homebrew": [
				"android-ndk"
			],
			"NPM": [ ],
			"Pipx": [ ],
			"Env": [
				"ANDROID_ROOT",
				"ANDROID_NDK_ROOT",
				"ANDROID_SDK_ROOT",
				"ANDROID_HOME"
			],
			"PathLinux": [
				"/usr/local/lib/android"
			],
			"PathMacOS": [
				"/Users/runner/Library/Android"
			],
			"PathWindows": [
				"C:\\Program Files (x86)\\Android",
				"C:\\Android"
			]
		},
		{
			"Name": "Ansible",
			"Description": "Ansible",
			"Postpone": 0,
			"APT": [ ],
			"Chocolatey": [ ],
			"Homebrew": [
				"ansible"
			],
			"NPM": [ ],
			"Pipx": [
				"ansible-core"
			],
			"Env": [ ],
			"PathLinux": [ ],
			"PathMacOS": [ ],
			"PathWindows": [ ]
		},
		{
			"Name": "ApacheAnt",
			"Description": "Apache Ant",
			"Postpone": 0,
			"APT": [
				"ant-optional",
				"ant"
			],
			"Chocolatey": [
				"ant"
			],
			"Homebrew": [
				"ant"
			],
			"NPM": [ ],
			"Pipx": [ ],
			"Env": [
				"ANT_HOME"
			],
			"PathLinux": [
				"/usr/share/ant"
			],
			"PathMacOS": [ ],
			"PathWindows": [ ]
		},
		{
			"Name": "ApacheHTTPD",
			"Description": "Apache HTTPD",
			"Postpone": 0,
			"APT": [
				"apache2",
				"^apache2-.*"
			],
			"Chocolatey": [
				"apache-httpd"
			],
			"Homebrew": [
				"httpd"
			],
			"NPM": [ ],
			"Pipx": [ ],
			"Env": [ ],
			"PathLinux": [ ],
			"PathMacOS": [
				"/usr/local/etc/httpd"
			],
			"PathWindows": [
				"C:\\tools\\Apache*"
			]
		},
		{
			"Name": "ASPDotNet",
			"Description": "ASP .Net",
			"Postpone": 0,
			"APT": [
				"^aspnetcore-.*"
			],
			"Chocolatey": [ ],
			"Homebrew": [ ],
			"NPM": [ ],
			"Pipx": [ ],
			"Env": [ ],
			"PathLinux": [ ],
			"PathMacOS": [ ],
			"PathWindows": [ ]
		},
		{
			"Name": "AWS",
			"Description": "AWS (Amazon Web Service)",
			"Postpone": 0,
			"APT": [ ],
			"Chocolatey": [ ],
			"Homebrew": [
				"aws-sam-cli",
				"session-manager-plugin"
			],
			"NPM": [ ],
			"Pipx": [ ],
			"Env": [ ],
			"PathLinux": [
				"/usr/local/aws-cli"
			],
			"PathMacOS": [ ],
			"PathWindows": [ ]
		},
		{
			"Name": "AzCopy",
			"Description": "AzCopy",
			"Postpone": 0,
			"APT": [ ],
			"Chocolatey": [
				"azcopy10"
			],
			"Homebrew": [
				"azcopy"
			],
			"NPM": [ ],
			"Pipx": [ ],
			"Env": [ ],
			"PathLinux": [
				"/usr/local/bin/azcopy"
			],
			"PathMacOS": [
				"/usr/local/bin/azcopy"
			],
			"PathWindows": [ ]
		},
		{
			"Name": "Azure",
			"Description": "Azure",
			"Postpone": 1,
			"APT": [
				"azure-cli"
			],
			"Chocolatey": [ ],
			"Homebrew": [
				"azure-cli"
			],
			"NPM": [ ],
			"Pipx": [ ],
			"Env": [
				"AZURE_EXTENSION_DIR"
			],
			"PathLinux": [
				"/opt/az/azcliextensions"
			],
			"PathMacOS": [ ],
			"PathWindows": [ ]
		},
		{
			"Name": "Bazel",
			"Description": "Bazel",
			"Postpone": 1,
			"APT": [ ],
			"Chocolatey": [ ],
			"Homebrew": [
				"bazel"
			],
			"NPM": [ ],
			"Pipx": [ ],
			"Env": [ ],
			"PathLinux": [
				"/usr/local/bin/bazel"
			],
			"PathMacOS": [ ],
			"PathWindows": [ ]
		},
		{
			"Name": "Bazelisk",
			"Description": "Bazelisk",
			"Postpone": 0,
			"APT": [ ],
			"Chocolatey": [ ],
			"Homebrew": [
				"bazelisk"
			],
			"NPM": [
				"@bazel/bazelisk"
			],
			"Pipx": [ ],
			"Env": [ ],
			"PathLinux": [ ],
			"PathMacOS": [ ],
			"PathWindows": [ ]
		},
		{
			"Name": "Bicep",
			"Description": "Azure Bicep",
			"Postpone": 0,
			"APT": [ ],
			"Chocolatey": [ ],
			"Homebrew": [
				"bicep"
			],
			"NPM": [ ],
			"Pipx": [ ],
			"Env": [ ],
			"PathLinux": [
				"/usr/local/bin/bicep"
			],
			"PathMacOS": [ ],
			"PathWindows": [ ]
		},
		{
			"Name": "Chromium",
			"Description": "Chromium",
			"Postpone": 0,
			"APT": [ ],
			"Chocolatey": [ ],
			"Homebrew": [
				"chromium"
			],
			"NPM": [ ],
			"Pipx": [ ],
			"Env": [
				"CHROMIUM_DIR"
			],
			"PathLinux": [
				"/usr/bin/chromium",
				"/usr/bin/chromium-browser",
				"/usr/local/share/chromium"
			],
			"PathMacOS": [ ],
			"PathWindows": [ ]
		},
		{
			"Name": "Clang",
			"Description": "Clang",
			"Postpone": 0,
			"APT": [
				"^clang-.*",
				"^clang-format-.*",
				"^clang-tidy-.*",
				"^lld-.*",
				"^lldb-.*"
			],
			"Chocolatey": [ ],
			"Homebrew": [ ],
			"NPM": [ ],
			"Pipx": [ ],
			"Env": [ ],
			"PathLinux": [ ],
			"PathMacOS": [ ],
			"PathWindows": [ ]
		},
		{
			"Name": "CodeQL",
			"Description": "CodeQL",
			"Postpone": 0,
			"APT": [ ],
			"Chocolatey": [ ],
			"Homebrew": [
				"codeql"
			],
			"NPM": [ ],
			"Pipx": [ ],
			"Env": [ ],
			"PathLinux": [
				"$Env:AGENT_TOOLSDIRECTORY/CodeQL",
				"/opt/hostedtoolcache/CodeQL"
			],
			"PathMacOS": [
				"$Env:AGENT_TOOLSDIRECTORY/CodeQL"
			],
			"PathWindows": [
				"$Env:AGENT_TOOLSDIRECTORY\\CodeQL"
			]
		},
		{
			"Name": "DotNet",
			"Description": ".Net",
			"Postpone": 1,
			"APT": [
				"^dotnet-.*"
			],
			"Chocolatey": [ ],
			"Homebrew": [
				"dotnet"
			],
			"NPM": [ ],
			"Pipx": [ ],
			"Env": [ ],
			"PathLinux": [
				"/usr/share/dotnet"
			],
			"PathMacOS": [
				"/usr/local/bin/dotnet",
				"$Env:HOME/.dotnet"
			],
			"PathWindows": [ ]
		},
		{
			"Name": "Erlang",
			"Description": "Erlang",
			"Postpone": 0,
			"APT": [
				"esl-erlang"
			],
			"Chocolatey": [ ],
			"Homebrew": [
				"erlang",
				"rebar3"
			],
			"NPM": [ ],
			"Pipx": [ ],
			"Env": [ ],
			"PathLinux": [
				"/usr/local/bin/rebar3"
			],
			"PathMacOS": [ ],
			"PathWindows": [ ]
		},
		{
			"Name": "Firefox",
			"Description": "Mozilla Firefox Browser",
			"Postpone": 0,
			"APT": [
				"firefox"
			],
			"Chocolatey": [ ],
			"Homebrew": [
				"firefox"
			],
			"NPM": [ ],
			"Pipx": [ ],
			"Env": [ ],
			"PathLinux": [ ],
			"PathMacOS": [ ],
			"PathWindows": [ ]
		},
		{
			"Name": "G++",
			"Description": "GNU C++ compiler",
			"Postpone": 0,
			"APT": [
				"^g\\+\\+.*"
			],
			"Chocolatey": [ ],
			"Homebrew": [ ],
			"NPM": [ ],
			"Pipx": [ ],
			"Env": [ ],
			"PathLinux": [ ],
			"PathMacOS": [ ],
			"PathWindows": [ ]
		},
		{
			"Name": "GCC",
			"Description": "GNU C compiler",
			"Postpone": 0,
			"APT": [
				"gcc",
				"^gcc-.*"
			],
			"Chocolatey": [ ],
			"Homebrew": [
				"gcc"
			],
			"NPM": [ ],
			"Pipx": [ ],
			"Env": [ ],
			"PathLinux": [ ],
			"PathMacOS": [ ],
			"PathWindows": [ ]
		},
		{
			"Name": "GeckoWebDriver",
			"Description": "Gecko Web Driver",
			"Postpone": 0,
			"APT": [ ],
			"Chocolatey": [ ],
			"Homebrew": [
				"geckodriver"
			],
			"NPM": [ ],
			"Pipx": [ ],
			"Env": [
				"GECKOWEBDRIVER"
			],
			"PathLinux": [
				"/usr/local/share/gecko_driver"
			],
			"PathMacOS": [
				"/usr/local/opt/geckodriver"
			],
			"PathWindows": [
				"C:\\SeleniumWebDrivers\\GeckoDriver"
			]
		},
		{
			"Name": "GFortran",
			"Description": "GNU Fortran",
			"Postpone": 0,
			"APT": [
				"gfortran",
				"^gfortran-.*"
			],
			"Chocolatey": [ ],
			"Homebrew": [ ],
			"NPM": [ ],
			"Pipx": [ ],
			"Env": [ ],
			"PathLinux": [ ],
			"PathMacOS": [ ],
			"PathWindows": [ ]
		},
		{
			"Name": "Go",
			"Description": "Go",
			"Postpone": 0,
			"APT": [ ],
			"Chocolatey": [ ],
			"Homebrew": [
				"go"
			],
			"NPM": [ ],
			"Pipx": [ ],
			"Env": [ ],
			"PathLinux": [
				"$Env:AGENT_TOOLSDIRECTORY/go",
				"/opt/hostedtoolcache/go"
			],
			"PathMacOS": [
				"$Env:AGENT_TOOLSDIRECTORY/go"
			],
			"PathWindows": [
				"$Env:AGENT_TOOLSDIRECTORY\\go"
			]
		},
		{
			"Name": "GoogleChrome",
			"Description": "Google Chrome Browser",
			"Postpone": 0,
			"APT": [
				"google-chrome-stable"
			],
			"Chocolatey": [ ],
			"Homebrew": [
				"google-chrome"
			],
			"NPM": [ ],
			"Pipx": [ ],
			"Env": [
				"CHROME_BIN"
			],
			"PathLinux": [
				"/usr/bin/google-chrome"
			],
			"PathMacOS": [ ],
			"PathWindows": [ ]
		},
		{
			"Name": "GoogleChromeWebDriver",
			"Description": "Google Chrome Web Driver",
			"Postpone": 0,
			"APT": [ ],
			"Chocolatey": [ ],
			"Homebrew": [
				"chromedriver"
			],
			"NPM": [ ],
			"Pipx": [ ],
			"Env": [
				"CHROMEWEBDRIVER",
				"CHROMEDRIVER_DIR"
			],
			"PathLinux": [
				"/usr/bin/chromedriver",
				"/usr/local/share/chrome_driver"
			],
			"PathMacOS": [
				"/usr/local/Caskroom/chromedriver"
			],
			"PathWindows": [
				"C:\\SeleniumWebDrivers\\ChromeDriver"
			]
		},
		{
			"Name": "GoogleCloudSDK",
			"Description": "Google Cloud SDK",
			"Postpone": 0,
			"APT": [
				"google-cloud-sdk"
			],
			"Chocolatey": [ ],
			"Homebrew": [
				"google-cloud-sdk"
			],
			"NPM": [ ],
			"Pipx": [ ],
			"Env": [ ],
			"PathLinux": [ ],
			"PathMacOS": [ ],
			"PathWindows": [ ]
		},
		{
			"Name": "Gradle",
			"Description": "Gradle",
			"Postpone": 0,
			"APT": [ ],
			"Chocolatey": [ ],
			"Homebrew": [
				"gradle"
			],
			"NPM": [ ],
			"Pipx": [ ],
			"Env": [ ],
			"PathLinux": [
				"/usr/bin/gradle",
				"/usr/share/gradle-*"
			],
			"PathMacOS": [ ],
			"PathWindows": [ ]
		},
		{
			"Name": "Grunt",
			"Description": "Grunt",
			"Postpone": 0,
			"APT": [ ],
			"Chocolatey": [ ],
			"Homebrew": [
				"grunt-cli"
			],
			"NPM": [
				"grunt",
				"grunt-cli"
			],
			"Pipx": [ ],
			"Env": [ ],
			"PathLinux": [ ],
			"PathMacOS": [ ],
			"PathWindows": [ ]
		},
		{
			"Name": "Gulp",
			"Description": "Gulp",
			"Postpone": 0,
			"APT": [ ],
			"Chocolatey": [ ],
			"Homebrew": [
				"gulp-cli"
			],
			"NPM": [
				"gulp",
				"gulp-cli"
			],
			"Pipx": [ ],
			"Env": [ ],
			"PathLinux": [ ],
			"PathMacOS": [ ],
			"PathWindows": [ ]
		},
		{
			"Name": "HaskellGHC",
			"Description": "Haskell GHC",
			"Postpone": 0,
			"APT": [ ],
			"Chocolatey": [ ],
			"Homebrew": [ ],
			"NPM": [ ],
			"Pipx": [ ],
			"Env": [ ],
			"PathLinux": [
				"/opt/ghc",
				"/usr/local/.ghcup/ghc"
			],
			"PathMacOS": [ ],
			"PathWindows": [ ]
		},
		{
			"Name": "Heroku",
			"Description": "Heroku",
			"Postpone": 0,
			"APT": [ ],
			"Chocolatey": [ ],
			"Homebrew": [ ],
			"NPM": [ ],
			"Pipx": [ ],
			"Env": [ ],
			"PathLinux": [
				"/usr/local/lib/heroku"
			],
			"PathMacOS": [
				"/usr/local/lib/heroku"
			],
			"PathWindows": [ ]
		},
		{
			"Name": "HHVM",
			"Description": "HipHop Virtual Machine",
			"Postpone": 0,
			"APT": [
				"hhvm"
			],
			"Chocolatey": [ ],
			"Homebrew": [ ],
			"NPM": [ ],
			"Pipx": [ ],
			"Env": [ ],
			"PathLinux": [ ],
			"PathMacOS": [ ],
			"PathWindows": [ ]
		},
		{
			"Name": "ImageMagick",
			"Description": "ImageMagick",
			"Postpone": 0,
			"APT": [
				"imagemagick",
				"^imagemagick-.*"
			],
			"Chocolatey": [ ],
			"Homebrew": [ ],
			"NPM": [ ],
			"Pipx": [ ],
			"Env": [ ],
			"PathLinux": [ ],
			"PathMacOS": [ ],
			"PathWindows": [ ]
		},
		{
			"Name": "Java/8",
			"Description": "Java 8",
			"Postpone": 0,
			"APT": [
				"temurin-8-jdk"
			],
			"Chocolatey": [ ],
			"Homebrew": [ ],
			"NPM": [ ],
			"Pipx": [ ],
			"Env": [
				"JAVA_HOME_8_X64"
			],
			"PathLinux": [
				"/usr/lib/jvm/*-8.*-*-*"
			],
			"PathMacOS": [
				"$Env:AGENT_TOOLSDIRECTORY/Java_*_jdk/8.*"
			],
			"PathWindows": [
				"$Env:AGENT_TOOLSDIRECTORY\\Java_*_jdk\\8.*"
			]
		},
		{
			"Name": "Java/11",
			"Description": "Java 11",
			"Postpone": 0,
			"APT": [
				"temurin-11-jdk"
			],
			"Chocolatey": [ ],
			"Homebrew": [ ],
			"NPM": [ ],
			"Pipx": [ ],
			"Env": [
				"JAVA_HOME_11_X64"
			],
			"PathLinux": [
				"/usr/lib/jvm/*-11.*-*-*"
			],
			"PathMacOS": [
				"$Env:AGENT_TOOLSDIRECTORY/Java_*_jdk/11.*"
			],
			"PathWindows": [
				"$Env:AGENT_TOOLSDIRECTORY\\Java_*_jdk\\11.*"
			]
		},
		{
			"Name": "Java/13",
			"Description": "Java 13",
			"Postpone": 0,
			"APT": [ ],
			"Chocolatey": [ ],
			"Homebrew": [ ],
			"NPM": [ ],
			"Pipx": [ ],
			"Env": [
				"JAVA_HOME_13_X64"
			],
			"PathLinux": [
				"/usr/lib/jvm/*-13.*-*-*"
			],
			"PathMacOS": [
				"$Env:AGENT_TOOLSDIRECTORY/Java_*_jdk/13.*"
			],
			"PathWindows": [
				"$Env:AGENT_TOOLSDIRECTORY\\Java_*_jdk\\13.*"
			]
		},
		{
			"Name": "Java/17",
			"Description": "Java 17",
			"Postpone": 0,
			"APT": [
				"temurin-17-jdk"
			],
			"Chocolatey": [ ],
			"Homebrew": [ ],
			"NPM": [ ],
			"Pipx": [ ],
			"Env": [
				"JAVA_HOME_17_X64"
			],
			"PathLinux": [
				"/usr/lib/jvm/*-17.*-*-*"
			],
			"PathMacOS": [
				"$Env:AGENT_TOOLSDIRECTORY/Java_*_jdk/17.*"
			],
			"PathWindows": [
				"$Env:AGENT_TOOLSDIRECTORY\\Java_*_jdk\\17.*"
			]
		},
		{
			"Name": "Java/All",
			"Description": "Java (All)",
			"Postpone": 1,
			"APT": [
				"^java-.*",
				".*-jdk$"
			],
			"Chocolatey": [ ],
			"Homebrew": [ ],
			"NPM": [ ],
			"Pipx": [ ],
			"Env": [
				"JAVA_HOME"
			],
			"PathLinux": [
				"/usr/lib/jvm"
			],
			"PathMacOS": [
				"$Env:AGENT_TOOLSDIRECTORY/Java_*_jdk"
			],
			"PathWindows": [
				"$Env:AGENT_TOOLSDIRECTORY\\Java_*_jdk"
			]
		},
		{
			"Name": "Julia",
			"Description": "Julia",
			"Postpone": 0,
			"APT": [ ],
			"Chocolatey": [
				"julia"
			],
			"Homebrew": [
				"julia"
			],
			"NPM": [ ],
			"Pipx": [ ],
			"Env": [ ],
			"PathLinux": [
				"/usr/local/julia*",
				"/usr/bin/julia"
			],
			"PathMacOS": [ ],
			"PathWindows": [ ]
		},
		{
			"Name": "Kotlin",
			"Description": "Kotlin",
			"Postpone": 0,
			"APT": [ ],
			"Chocolatey": [ ],
			"Homebrew": [
				"kotlin"
			],
			"NPM": [ ],
			"Pipx": [ ],
			"Env": [ ],
			"PathLinux": [
				"/usr/share/kotlinc"
			],
			"PathMacOS": [ ],
			"PathWindows": [ ]
		},
		{
			"Name": "Leiningen",
			"Description": "Leiningen",
			"Postpone": 0,
			"APT": [ ],
			"Chocolatey": [ ],
			"Homebrew": [ ],
			"NPM": [ ],
			"Pipx": [ ],
			"Env": [
				"LEIN_HOME"
			],
			"PathLinux": [
				"/usr/local/bin/lein"
			],
			"PathMacOS": [ ],
			"PathWindows": [ ]
		},
		{
			"Name": "Lerna",
			"Description": "Lerna",
			"Postpone": 0,
			"APT": [ ],
			"Chocolatey": [ ],
			"Homebrew": [
				"lerna"
			],
			"NPM": [
				"lerna"
			],
			"Pipx": [ ],
			"Env": [ ],
			"PathLinux": [ ],
			"PathMacOS": [ ],
			"PathWindows": [ ]
		},
		{
			"Name": "LLVM",
			"Description": "LLVM",
			"Postpone": 0,
			"APT": [
				"^llvm-.*"
			],
			"Chocolatey": [
				"llvm"
			],
			"Homebrew": [
				"llvm"
			],
			"NPM": [ ],
			"Pipx": [ ],
			"Env": [ ],
			"PathLinux": [ ],
			"PathMacOS": [ ],
			"PathWindows": [ ]
		},
		{
			"Name": "Maven",
			"Description": "Maven",
			"Postpone": 0,
			"APT": [ ],
			"Chocolatey": [ ],
			"Homebrew": [
				"maven"
			],
			"NPM": [ ],
			"Pipx": [ ],
			"Env": [ ],
			"PathLinux": [
				"/usr/bin/mvn",
				"/usr/share/apache-maven-*"
			],
			"PathMacOS": [ ],
			"PathWindows": [ ]
		},
		{
			"Name": "MicrosoftEdge",
			"Description": "Microsoft Edge",
			"Postpone": 0,
			"APT": [
				"microsoft-edge-stable"
			],
			"Chocolatey": [ ],
			"Homebrew": [
				"microsoft-edge"
			],
			"NPM": [ ],
			"Pipx": [ ],
			"Env": [ ],
			"PathLinux": [ ],
			"PathMacOS": [
				"/Applications/Microsoft Edge.app"
			],
			"PathWindows": [ ]
		},
		{
			"Name": "MicrosoftEdgeWebDriver",
			"Description": "Microsoft Edge Web Driver",
			"Postpone": 0,
			"APT": [ ],
			"Chocolatey": [ ],
			"Homebrew": [ ],
			"NPM": [ ],
			"Pipx": [ ],
			"Env": [
				"EDGEWEBDRIVER"
			],
			"PathLinux": [
				"/usr/bin/edgedriver",
				"/usr/local/share/edge_driver"
			],
			"PathMacOS": [
				"/usr/local/bin/msedgedriver",
				"/usr/local/share/edge_driver"
			],
			"PathWindows": [
				"C:\\SeleniumWebDrivers\\EdgeDriver"
			]
		},
		{
			"Name": "MicrosoftInternetExplorerWebDriver",
			"Description": "Microsoft Internet Explorer Web Driver",
			"Postpone": 0,
			"APT": [ ],
			"Chocolatey": [ ],
			"Homebrew": [ ],
			"NPM": [ ],
			"Pipx": [ ],
			"Env": [
				"IEWEBDRIVER"
			],
			"PathLinux": [ ],
			"PathMacOS": [ ],
			"PathWindows": [
				"C:\\SeleniumWebDrivers\\IEDriver"
			]
		},
		{
			"Name": "Miniconda",
			"Description": "Mini Conda",
			"Postpone": 0,
			"APT": [ ],
			"Chocolatey": [ ],
			"Homebrew": [
				"miniconda"
			],
			"NPM": [ ],
			"Pipx": [ ],
			"Env": [
				"CONDA"
			],
			"PathLinux": [
				"/usr/share/miniconda",
				"/usr/bin/conda"
			],
			"PathMacOS": [
				"/usr/local/miniconda",
				"/usr/local/bin/conda",
				"$Env:HOME/.conda"
			],
			"PathWindows": [
				"C:\\Miniconda"
			]
		},
		{
			"Name": "MongoDB",
			"Description": "MongoDB",
			"Postpone": 0,
			"APT": [
				"^mongodb-.*"
			],
			"Chocolatey": [ ],
			"Homebrew": [ ],
			"NPM": [ ],
			"Pipx": [ ],
			"Env": [ ],
			"PathLinux": [ ],
			"PathMacOS": [ ],
			"PathWindows": [ ]
		},
		{
			"Name": "Mono",
			"Description": "Mono",
			"Postpone": 0,
			"APT": [
				"^mono-.*",
				"^monodoc-.*"
			],
			"Chocolatey": [ ],
			"Homebrew": [
				"mono"
			],
			"NPM": [ ],
			"Pipx": [ ],
			"Env": [ ],
			"PathLinux": [ ],
			"PathMacOS": [ ],
			"PathWindows": [ ]
		},
		{
			"Name": "MSSQL",
			"Description": "MS SQL",
			"Postpone": 0,
			"APT": [
				"mssql-tools",
				"unixodbc-dev"
			],
			"Chocolatey": [ ],
			"Homebrew": [ ],
			"NPM": [ ],
			"Pipx": [ ],
			"Env": [ ],
			"PathLinux": [
				"/opt/mssql-tools"
			],
			"PathMacOS": [ ],
			"PathWindows": [
				"$Env:PROGRAMFILES\\Microsoft SQL Server\\"
			]
		},
		{
			"Name": "MSYS2",
			"Description": "MSYS2 Pacman",
			"Postpone": 9,
			"APT": [ ],
			"Chocolatey": [ ],
			"Homebrew": [ ],
			"NPM": [ ],
			"Pipx": [ ],
			"Env": [ ],
			"PathLinux": [ ],
			"PathMacOS": [ ],
			"PathWindows": [
				"C:\\msys64"
			]
		},
		{
			"Name": "MySQL",
			"Description": "MySQL",
			"Postpone": 0,
			"APT": [
				"^mysql-.*",
				"libmysqlclient-dev"
			],
			"Chocolatey": [ ],
			"Homebrew": [
				"mysql-client",
				"mysql"
			],
			"NPM": [ ],
			"Pipx": [ ],
			"Env": [ ],
			"PathLinux": [ ],
			"PathMacOS": [ ],
			"PathWindows": [ ]
		},
		{
			"Name": "Netlify",
			"Description": "Netlify",
			"Postpone": 0,
			"APT": [ ],
			"Chocolatey": [ ],
			"Homebrew": [
				"netlify-cli"
			],
			"NPM": [
				"netlify"
			],
			"Pipx": [ ],
			"Env": [ ],
			"PathLinux": [ ],
			"PathMacOS": [ ],
			"PathWindows": [ ]
		},
		{
			"Name": "Newman",
			"Description": "Newman",
			"Postpone": 0,
			"APT": [ ],
			"Chocolatey": [ ],
			"Homebrew": [ ],
			"NPM": [
				"newman"
			],
			"Pipx": [ ],
			"Env": [ ],
			"PathLinux": [ ],
			"PathMacOS": [ ],
			"PathWindows": [ ]
		},
		{
			"Name": "Nginx",
			"Description": "Nginx",
			"Postpone": 0,
			"APT": [
				"nginx"
			],
			"Chocolatey": [ ],
			"Homebrew": [
				"nginx"
			],
			"NPM": [ ],
			"Pipx": [ ],
			"Env": [ ],
			"PathLinux": [ ],
			"PathMacOS": [
				"/usr/local/etc/nginx"
			],
			"PathWindows": [
				"C:\\tools\\nginx*"
			]
		},
		{
			"Name": "OpenGLDRI",
			"Description": "OpenGL API DRI Modules",
			"Postpone": 0,
			"APT": [
				"libgl1-mesa-dri"
			],
			"Chocolatey": [ ],
			"Homebrew": [ ],
			"NPM": [ ],
			"Pipx": [ ],
			"Env": [ ],
			"PathLinux": [ ],
			"PathMacOS": [ ],
			"PathWindows": [ ]
		},
		{
			"Name": "OpenShiftClient",
			"Description": "OpenShift Client",
			"Postpone": 0,
			"APT": [ ],
			"Chocolatey": [ ],
			"Homebrew": [ ],
			"NPM": [ ],
			"Pipx": [ ],
			"Env": [ ],
			"PathLinux": [
				"/usr/local/bin/oc"
			],
			"PathMacOS": [ ],
			"PathWindows": [ ]
		},
		{
			"Name": "Packer",
			"Description": "Packer",
			"Postpone": 0,
			"APT": [ ],
			"Chocolatey": [ ],
			"Homebrew": [ ],
			"NPM": [ ],
			"Pipx": [ ],
			"Env": [ ],
			"PathLinux": [
				"/usr/local/bin/packer"
			],
			"PathMacOS": [ ],
			"PathWindows": [ ]
		},
		{
			"Name": "Parcel",
			"Description": "Parcel",
			"Postpone": 0,
			"APT": [ ],
			"Chocolatey": [ ],
			"Homebrew": [ ],
			"NPM": [
				"parcel"
			],
			"Pipx": [ ],
			"Env": [ ],
			"PathLinux": [ ],
			"PathMacOS": [ ],
			"PathWindows": [ ]
		},
		{
			"Name": "Perl",
			"Description": "Perl",
			"Postpone": 0,
			"APT": [
				"^perl.*"
			],
			"Chocolatey": [ ],
			"Homebrew": [ ],
			"NPM": [ ],
			"Pipx": [ ],
			"Env": [ ],
			"PathLinux": [ ],
			"PathMacOS": [ ],
			"PathWindows": [ ]
		},
		{
			"Name": "PhantomJS",
			"Description": "Phantom JS",
			"Postpone": 0,
			"APT": [
				"phantomjs"
			],
			"Chocolatey": [ ],
			"Homebrew": [ ],
			"NPM": [ ],
			"Pipx": [ ],
			"Env": [ ],
			"PathLinux": [
				"/usr/local/share/phantomjs*",
				"/usr/local/bin/phantomjs"
			],
			"PathMacOS": [ ],
			"PathWindows": [ ]
		},
		{
			"Name": "PHP",
			"Description": "PHP",
			"Postpone": 0,
			"APT": [
				"^php.*",
				"snmp"
			],
			"Chocolatey": [ ],
			"Homebrew": [ ],
			"NPM": [ ],
			"Pipx": [ ],
			"Env": [ ],
			"PathLinux": [
				"/usr/local/bin/phpunit"
			],
			"PathMacOS": [ ],
			"PathWindows": [ ]
		},
		{
			"Name": "Pipx",
			"Description": "Pipx",
			"Postpone": 9,
			"APT": [ ],
			"Chocolatey": [ ],
			"Homebrew": [ ],
			"NPM": [ ],
			"Pipx": [ ],
			"Env": [
				"PIPX_BIN_DIR",
				"PIPX_HOME"
			],
			"PathLinux": [ ],
			"PathMacOS": [
				"/opt/pipx_bin"
			],
			"PathWindows": [
				"C:\\Program Files (x86)\\pipx",
				"C:\\Program Files (x86)\\pipx_bin"
			]
		},
		{
			"Name": "PostgreSQL",
			"Description": "PostgreSQL",
			"Postpone": 0,
			"APT": [
				"^postgresql-.*",
				"libpq-dev"
			],
			"Chocolatey": [ ],
			"Homebrew": [ ],
			"NPM": [ ],
			"Pipx": [ ],
			"Env": [
				"PGBIN",
				"PGDATA",
				"PGROOT"
			],
			"PathLinux": [ ],
			"PathMacOS": [ ],
			"PathWindows": [
				"C:\\Program Files\\PostgreSQL"
			]
		},
		{
			"Name": "Pulumi",
			"Description": "Pulumi",
			"Postpone": 0,
			"APT": [ ],
			"Chocolatey": [ ],
			"Homebrew": [ ],
			"NPM": [ ],
			"Pipx": [ ],
			"Env": [ ],
			"PathLinux": [
				"/usr/local/bin/pulumi*"
			],
			"PathMacOS": [ ],
			"PathWindows": [ ]
		},
		{
			"Name": "R",
			"Description": "R",
			"Postpone": 0,
			"APT": [
				"r-base",
				"^r-base-.*"
			],
			"Chocolatey": [ ],
			"Homebrew": [ ],
			"NPM": [ ],
			"Pipx": [ ],
			"Env": [ ],
			"PathLinux": [ ],
			"PathMacOS": [ ],
			"PathWindows": [ ]
		},
		{
			"Name": "Ruby",
			"Description": "Ruby",
			"Postpone": 0,
			"APT": [
				"ruby",
				"ruby3.0",
				"^ruby-.*",
				"^ruby3.0-.*"
			],
			"Chocolatey": [ ],
			"Homebrew": [ ],
			"NPM": [ ],
			"Pipx": [ ],
			"Env": [ ],
			"PathLinux": [ ],
			"PathMacOS": [ ],
			"PathWindows": [ ]
		},
		{
			"Name": "Selenium",
			"Description": "Selenium",
			"Postpone": 0,
			"APT": [ ],
			"Chocolatey": [ ],
			"Homebrew": [ ],
			"NPM": [ ],
			"Pipx": [ ],
			"Env": [
				"SELENIUM_JAR_PATH"
			],
			"PathLinux": [
				"/usr/share/java/selenium-server.jar"
			],
			"PathMacOS": [ ],
			"PathWindows": [
				"C:\\selenium\\selenium-server.jar"
			]
		},
		{
			"Name": "Sphinx",
			"Description": "Sphinx",
			"Postpone": 0,
			"APT": [
				"sphinxsearch"
			],
			"Chocolatey": [ ],
			"Homebrew": [ ],
			"NPM": [ ],
			"Pipx": [ ],
			"Env": [ ],
			"PathLinux": [ ],
			"PathMacOS": [ ],
			"PathWindows": [ ]
		},
		{
			"Name": "SQLPackage",
			"Description": "SQL Package",
			"Postpone": 0,
			"APT": [ ],
			"Chocolatey": [ ],
			"Homebrew": [ ],
			"NPM": [ ],
			"Pipx": [ ],
			"Env": [ ],
			"PathLinux": [
				"/usr/local/bin/sqlpackage",
				"/usr/local/sqlpackage"
			],
			"PathMacOS": [ ],
			"PathWindows": [ ]
		},
		{
			"Name": "Stack",
			"Description": "Stack",
			"Postpone": 0,
			"APT": [ ],
			"Chocolatey": [ ],
			"Homebrew": [ ],
			"NPM": [ ],
			"Pipx": [ ],
			"Env": [ ],
			"PathLinux": [
				"$Env:AGENT_TOOLSDIRECTORY/stack",
				"/opt/hostedtoolcache/stack"
			],
			"PathMacOS": [
				"$Env:AGENT_TOOLSDIRECTORY/stack"
			],
			"PathWindows": [
				"$Env:AGENT_TOOLSDIRECTORY\\stack"
			]
		},
		{
			"Name": "Swift",
			"Description": "Swift",
			"Postpone": 0,
			"APT": [ ],
			"Chocolatey": [ ],
			"Homebrew": [
				"swiftformat"
			],
			"NPM": [ ],
			"Pipx": [ ],
			"Env": [
				"SWIFT_PATH"
			],
			"PathLinux": [
				"/usr/local/bin/swift*",
				"/usr/local/bin/swiftc",
				"/usr/share/swift*"
			],
			"PathMacOS": [ ],
			"PathWindows": [ ]
		},
		{
			"Name": "Terraform",
			"Description": "Terraform",
			"Postpone": 0,
			"APT": [ ],
			"Chocolatey": [ ],
			"Homebrew": [ ],
			"NPM": [ ],
			"Pipx": [ ],
			"Env": [ ],
			"PathLinux": [
				"/usr/local/bin/terraform"
			],
			"PathMacOS": [ ],
			"PathWindows": [ ]
		},
		{
			"Name": "VCPkg",
			"Description": "VCPkg",
			"Postpone": 9,
			"APT": [ ],
			"Chocolatey": [ ],
			"Homebrew": [ ],
			"NPM": [ ],
			"Pipx": [ ],
			"Env": [
				"VCPKG_INSTALLATION_ROOT"
			],
			"PathLinux": [
				"/usr/local/share/vcpkg",
				"/root/.vcpkg"
			],
			"PathMacOS": [
				"/usr/local/bin/vcpkg",
				"/usr/local/share/vcpkg"
			],
			"PathWindows": [
				"C:\\vcpkg"
			]
		},
		{
			"Name": "Vercel",
			"Description": "Vercel",
			"Postpone": 0,
			"APT": [ ],
			"Chocolatey": [ ],
			"Homebrew": [ ],
			"NPM": [
				"vercel"
			],
			"Pipx": [ ],
			"Env": [ ],
			"PathLinux": [ ],
			"PathMacOS": [ ],
			"PathWindows": [ ]
		},
		{
			"Name": "VisualStudio/2019",
			"Description": "Visual Studio 2019",
			"Postpone": 0,
			"APT": [ ],
			"Chocolatey": [ ],
			"Homebrew": [ ],
			"NPM": [ ],
			"Pipx": [ ],
			"Env": [ ],
			"PathLinux": [ ],
			"PathMacOS": [
				"/Applications/Visual Studio 2019*"
			],
			"PathWindows": [
				"C:\\Program Files\\Microsoft Visual Studio\\2019"
			]
		},
		{
			"Name": "VisualStudio/2022",
			"Description": "Visual Studio 2022",
			"Postpone": 0,
			"APT": [ ],
			"Chocolatey": [ ],
			"Homebrew": [ ],
			"NPM": [ ],
			"Pipx": [ ],
			"Env": [ ],
			"PathLinux": [ ],
			"PathMacOS": [ ],
			"PathWindows": [
				"C:\\Program Files\\Microsoft Visual Studio\\2022"
			]
		},
		{
			"Name": "VisualStudio/All",
			"Description": "Visual Studio",
			"Postpone": 1,
			"APT": [ ],
			"Chocolatey": [ ],
			"Homebrew": [ ],
			"NPM": [ ],
			"Pipx": [ ],
			"Env": [ ],
			"PathLinux": [ ],
			"PathMacOS": [
				"/Applications/Visual Studio*"
			],
			"PathWindows": [
				"C:\\Program Files\\Microsoft Visual Studio",
				"C:\\ProgramData\\Microsoft\\VisualStudio"
			]
		},
		{
			"Name": "Webpack",
			"Description": "Webpack",
			"Postpone": 0,
			"APT": [ ],
			"Chocolatey": [ ],
			"Homebrew": [ ],
			"NPM": [
				"webpack-cli",
				"webpack"
			],
			"Pipx": [ ],
			"Env": [ ],
			"PathLinux": [ ],
			"PathMacOS": [ ],
			"PathWindows": [ ]
		},
		{
			"Name": "Xcode/8",
			"Description": "Xcode 8",
			"Postpone": 0,
			"APT": [ ],
			"Chocolatey": [ ],
			"Homebrew": [ ],
			"NPM": [ ],
			"Pipx": [ ],
			"Env": [ ],
			"PathLinux": [ ],
			"PathMacOS": [
				"/Applications/Xcode_8.app",
				"/Applications/Xcode8.app"
			],
			"PathWindows": [ ]
		},
		{
			"Name": "Xcode/8.1",
			"Description": "Xcode 8.1",
			"Postpone": 0,
			"APT": [ ],
			"Chocolatey": [ ],
			"Homebrew": [ ],
			"NPM": [ ],
			"Pipx": [ ],
			"Env": [ ],
			"PathLinux": [ ],
			"PathMacOS": [
				"/Applications/Xcode_8.1.app",
				"/Applications/Xcode81.app"
			],
			"PathWindows": [ ]
		},
		{
			"Name": "Xcode/9",
			"Description": "Xcode 9",
			"Postpone": 0,
			"APT": [ ],
			"Chocolatey": [ ],
			"Homebrew": [ ],
			"NPM": [ ],
			"Pipx": [ ],
			"Env": [ ],
			"PathLinux": [ ],
			"PathMacOS": [
				"/Applications/Xcode_9.app",
				"/Applications/Xcode9.app"
			],
			"PathWindows": [ ]
		},
		{
			"Name": "Xcode/9.1",
			"Description": "Xcode 9.1",
			"Postpone": 0,
			"APT": [ ],
			"Chocolatey": [ ],
			"Homebrew": [ ],
			"NPM": [ ],
			"Pipx": [ ],
			"Env": [ ],
			"PathLinux": [ ],
			"PathMacOS": [
				"/Applications/Xcode_9.1.app",
				"/Applications/Xcode91.app"
			],
			"PathWindows": [ ]
		},
		{
			"Name": "Xcode/9.2",
			"Description": "Xcode 9.2",
			"Postpone": 0,
			"APT": [ ],
			"Chocolatey": [ ],
			"Homebrew": [ ],
			"NPM": [ ],
			"Pipx": [ ],
			"Env": [ ],
			"PathLinux": [ ],
			"PathMacOS": [
				"/Applications/Xcode_9.2.app",
				"/Applications/Xcode92.app"
			],
			"PathWindows": [ ]
		},
		{
			"Name": "Xcode/9.3",
			"Description": "Xcode 9.3",
			"Postpone": 0,
			"APT": [ ],
			"Chocolatey": [ ],
			"Homebrew": [ ],
			"NPM": [ ],
			"Pipx": [ ],
			"Env": [ ],
			"PathLinux": [ ],
			"PathMacOS": [
				"/Applications/Xcode_9.3_beta.app",
				"/Applications/Xcode_9.3.app",
				"/Applications/Xcode93.app"
			],
			"PathWindows": [ ]
		},
		{
			"Name": "Xcode/9.4",
			"Description": "Xcode 9.4",
			"Postpone": 0,
			"APT": [ ],
			"Chocolatey": [ ],
			"Homebrew": [ ],
			"NPM": [ ],
			"Pipx": [ ],
			"Env": [ ],
			"PathLinux": [ ],
			"PathMacOS": [
				"/Applications/Xcode_9.4_beta_2.app",
				"/Applications/Xcode_9.4_beta.app",
				"/Applications/Xcode_9.4-beta.app",
				"/Applications/Xcode_9.4.app"
			],
			"PathWindows": [ ]
		},
		{
			"Name": "Xcode/11.7",
			"Description": "Xcode 11.7",
			"Postpone": 0,
			"APT": [ ],
			"Chocolatey": [ ],
			"Homebrew": [ ],
			"NPM": [ ],
			"Pipx": [ ],
			"Env": [ ],
			"PathLinux": [ ],
			"PathMacOS": [
				"/Applications/Xcode_11.7.app"
			],
			"PathWindows": [ ]
		},
		{
			"Name": "Xcode/12.4",
			"Description": "Xcode 12.4",
			"Postpone": 0,
			"APT": [ ],
			"Chocolatey": [ ],
			"Homebrew": [ ],
			"NPM": [ ],
			"Pipx": [ ],
			"Env": [ ],
			"PathLinux": [ ],
			"PathMacOS": [
				"/Applications/Xcode_12.4.app"
			],
			"PathWindows": [ ]
		},
		{
			"Name": "Xcode/12.5.1",
			"Description": "Xcode 12.5.1",
			"Postpone": 0,
			"APT": [ ],
			"Chocolatey": [ ],
			"Homebrew": [ ],
			"NPM": [ ],
			"Pipx": [ ],
			"Env": [ ],
			"PathLinux": [ ],
			"PathMacOS": [
				"/Applications/Xcode_12.5.1.app"
			],
			"PathWindows": [ ]
		},
		{
			"Name": "Xcode/13.0",
			"Description": "Xcode 13.0",
			"Postpone": 0,
			"APT": [ ],
			"Chocolatey": [ ],
			"Homebrew": [ ],
			"NPM": [ ],
			"Pipx": [ ],
			"Env": [ ],
			"PathLinux": [ ],
			"PathMacOS": [
				"/Applications/Xcode_13.0.app"
			],
			"PathWindows": [ ]
		},
		{
			"Name": "Xcode/13.1",
			"Description": "Xcode 13.1",
			"Postpone": 0,
			"APT": [ ],
			"Chocolatey": [ ],
			"Homebrew": [ ],
			"NPM": [ ],
			"Pipx": [ ],
			"Env": [ ],
			"PathLinux": [ ],
			"PathMacOS": [
				"/Applications/Xcode_13.1.app"
			],
			"PathWindows": [ ]
		},
		{
			"Name": "Xcode/13.2.1",
			"Description": "Xcode 13.2.1",
			"Postpone": 0,
			"APT": [ ],
			"Chocolatey": [ ],
			"Homebrew": [ ],
			"NPM": [ ],
			"Pipx": [ ],
			"Env": [ ],
			"PathLinux": [ ],
			"PathMacOS": [
				"/Applications/Xcode_13.2.1.app"
			],
			"PathWindows": [ ]
		},
		{
			"Name": "Xcode/13.3.1",
			"Description": "Xcode 13.3.1",
			"Postpone": 0,
			"APT": [ ],
			"Chocolatey": [ ],
			"Homebrew": [ ],
			"NPM": [ ],
			"Pipx": [ ],
			"Env": [ ],
			"PathLinux": [ ],
			"PathMacOS": [
				"/Applications/Xcode_13.3.1.app"
			],
			"PathWindows": [ ]
		},
		{
			"Name": "Xcode/13.4.1",
			"Description": "Xcode 13.4.1",
			"Postpone": 0,
			"APT": [ ],
			"Chocolatey": [ ],
			"Homebrew": [ ],
			"NPM": [ ],
			"Pipx": [ ],
			"Env": [ ],
			"PathLinux": [ ],
			"PathMacOS": [
				"/Applications/Xcode_13.4.1.app"
			],
			"PathWindows": [ ]
		},
		{
			"Name": "Xcode/14.0.1",
			"Description": "Xcode 14.0.1",
			"Postpone": 0,
			"APT": [ ],
			"Chocolatey": [ ],
			"Homebrew": [ ],
			"NPM": [ ],
			"Pipx": [ ],
			"Env": [ ],
			"PathLinux": [ ],
			"PathMacOS": [
				"/Applications/Xcode_14.0.1.app"
			],
			"PathWindows": [ ]
		},
		{
			"Name": "Xcode/14.1",
			"Description": "Xcode 14.1",
			"Postpone": 0,
			"APT": [ ],
			"Chocolatey": [ ],
			"Homebrew": [ ],
			"NPM": [ ],
			"Pipx": [ ],
			"Env": [ ],
			"PathLinux": [ ],
			"PathMacOS": [
				"/Applications/Xcode_14.1.app"
			],
			"PathWindows": [ ]
		},
		{
			"Name": "Xcode/14.2",
			"Description": "Xcode 14.2",
			"Postpone": 0,
			"APT": [ ],
			"Chocolatey": [ ],
			"Homebrew": [ ],
			"NPM": [ ],
			"Pipx": [ ],
			"Env": [ ],
			"PathLinux": [ ],
			"PathMacOS": [
				"/Applications/Xcode_14.2.app"
			],
			"PathWindows": [ ]
		},
		{
			"Name": "Xcode/14.3",
			"Description": "Xcode 14.3",
			"Postpone": 0,
			"APT": [ ],
			"Chocolatey": [ ],
			"Homebrew": [ ],
			"NPM": [ ],
			"Pipx": [ ],
			"Env": [ ],
			"PathLinux": [ ],
			"PathMacOS": [
				"/Applications/Xcode_14.3.app"
			],
			"PathWindows": [ ]
		},
		{
			"Name": "Xcode/14.3.1",
			"Description": "Xcode 14.3.1",
			"Postpone": 0,
			"APT": [ ],
			"Chocolatey": [ ],
			"Homebrew": [ ],
			"NPM": [ ],
			"Pipx": [ ],
			"Env": [ ],
			"PathLinux": [ ],
			"PathMacOS": [
				"/Applications/Xcode_14.3.1.app"
			],
			"PathWindows": [ ]
		},
		{
			"Name": "Xcode/15.0",
			"Description": "Xcode 15.0",
			"Postpone": 0,
			"APT": [ ],
			"Chocolatey": [ ],
			"Homebrew": [ ],
			"NPM": [ ],
			"Pipx": [ ],
			"Env": [ ],
			"PathLinux": [ ],
			"PathMacOS": [
				"/Applications/Xcode_15.0.app"
			],
			"PathWindows": [ ]
		},
		{
			"Name": "Xcode/All",
			"Description": "Xcode (All)",
			"Postpone": 1,
			"APT": [ ],
			"Chocolatey": [ ],
			"Homebrew": [ ],
			"NPM": [ ],
			"Pipx": [ ],
			"Env": [ ],
			"PathLinux": [ ],
			"PathMacOS": [
				"/Applications/Xcode*"
			],
			"PathWindows": [ ]
		},
		{
			"Name": "YAMLLint",
			"Description": "YAML Lint",
			"Postpone": 0,
			"APT": [ ],
			"Chocolatey": [ ],
			"Homebrew": [ ],
			"NPM": [ ],
			"Pipx": [
				"yamllint"
			],
			"Env": [ ],
			"PathLinux": [ ],
			"PathMacOS": [ ],
			"PathWindows": [ ]
		},
		{
			"Name": "Yarn",
			"Description": "Yarn",
			"Postpone": 0,
			"APT": [ ],
			"Chocolatey": [ ],
			"Homebrew": [ ],
			"NPM": [
				"yarn"
			],
			"Pipx": [ ],
			"Env": [ ],
			"PathLinux": [ ],
			"PathMacOS": [ ],
			"PathWindows": [ ]
		}
	]
}
